AUTHORS
ChangeLog
LICENSE
README.md
requirements.txt
setup.cfg
setup.py
examples/conf/yaml_conf.py
examples/datetime/dt.py
examples/email/send.py
examples/exception/retry.py
examples/file/audio.py
examples/file/base.py
examples/file/image.py
examples/file/video.py
examples/log/log1.py
examples/redis/basic.py
examples/redis/cache.py
examples/redis/limiter.py
examples/redis/locker.py
examples/track/__init__.py
examples/track/run.py
examples/track/test.py
examples/xlsx/reader.py
examples/xlsx/writer.py
examples/zip/package.py
open_box/__init__.py
open_box.egg-info/PKG-INFO
open_box.egg-info/SOURCES.txt
open_box.egg-info/dependency_links.txt
open_box.egg-info/not-zip-safe
open_box.egg-info/pbr.json
open_box.egg-info/requires.txt
open_box.egg-info/top_level.txt
open_box/conf/__init__.py
open_box/conf/yaml_loader.py
open_box/datetime/__init__.py
open_box/email/__init__.py
open_box/enum/__init__.py
open_box/enum/enum.py
open_box/exception/__init__.py
open_box/exception/retry.py
open_box/file/__init__.py
open_box/file/audio.py
open_box/file/error.py
open_box/file/image.py
open_box/file/video.py
open_box/log/__init__.py
open_box/log/formatter.py
open_box/log/handler.py
open_box/redis/__init__.py
open_box/redis/cache.py
open_box/redis/limiter.py
open_box/redis/locker.py
open_box/track/__init__.py
open_box/xlsx/__init__.py
open_box/xlsx/reader.py
open_box/xlsx/writer.py
open_box/zip/__init__.py