Metadata-Version: 1.0
Name: open-box
Version: 1.0.11.dev26
Summary: "this is web development utils"
Home-page: UNKNOWN
Author: HNF
Author-email: 369685930@qq.com
License: MIT
Platform: UNKNOWN
